nautobot_version_control/__init__.py
nautobot_version_control/admin.py
nautobot_version_control/api/__init__.py
nautobot_version_control/api/serializers.py
nautobot_version_control/api/urls.py
nautobot_version_control/api/views.py
nautobot_version_control/banner.py
nautobot_version_control/constants.py
nautobot_version_control/custom_validators.py
nautobot_version_control/datasources.py
nautobot_version_control/diffs.py
nautobot_version_control/dynamic/__init__.py
nautobot_version_control/dynamic/diff_factory.py
nautobot_version_control/filters.py
nautobot_version_control/forms.py
nautobot_version_control/functions.py
nautobot_version_control/graphql/types.py
nautobot_version_control/jobs.py
nautobot_version_control/management/commands/cleanup_data.py
nautobot_version_control/merge.py
nautobot_version_control/middleware.py
nautobot_version_control/migrations/0001_initial.py
nautobot_version_control/migrations/0002_branchmeta.py
nautobot_version_control/migrations/0003_conflicts.py
nautobot_version_control/migrations/0004_constraintviolations.py
nautobot_version_control/migrations/0005_pullrequest_pullrequestreview.py
nautobot_version_control/migrations/0006_auto_20210817_0251.py
nautobot_version_control/migrations/0007_auto_20210818_1708.py
nautobot_version_control/migrations/__init__.py
nautobot_version_control/models.py
nautobot_version_control/navigation.py
nautobot_version_control/routers.py
nautobot_version_control/tables.py
nautobot_version_control/template_content.py
nautobot_version_control/templates/nautobot_version_control/branch.html
nautobot_version_control/templates/nautobot_version_control/branch_bulk_delete.html
nautobot_version_control/templates/nautobot_version_control/branch_edit.html
nautobot_version_control/templates/nautobot_version_control/branch_list.html
nautobot_version_control/templates/nautobot_version_control/branch_merge.html
nautobot_version_control/templates/nautobot_version_control/branch_merge_preview.html
nautobot_version_control-0.1.0.dist-info/LICENSE.txt
nautobot_version_control-0.1.0.dist-info/WHEEL
nautobot_version_control-0.1.0.dist-info/METADATA
nautobot_version_control-0.1.0.dist-info/RECORD
