Metadata-Version: 2.1
Name: nautobot-version-control
Version: 0.1.0
Summary: Nautobot Version Control
License: LICENSE.txt
Author: Network to Code, LLC
Author-email: opensource@networktocode.com
Requires-Python: >=3.6.2,<4.0.0
Classifier: License :: Other/Proprietary License
Classifier: Programming Language :: Python :: 3
Classifier: Programming Language :: Python :: 3.7
Classifier: Programming Language :: Python :: 3.8
Classifier: Programming Language :: Python :: 3.9
Requires-Dist: mysqlclient (>=2.0.3,<3.0.0)
Requires-Dist: nautobot (>=1.2.0b1,<1.3.0)
